pydf/__init__.py
pydf/version.py
pydf/wkhtmltopdf.py
pydf/bin/wkhtmltopdf
python_pdf-0.38.dist-info/LICENSE
python_pdf-0.38.dist-info/METADATA
python_pdf-0.38.dist-info/WHEEL
python_pdf-0.38.dist-info/top_level.txt
python_pdf-0.38.dist-info/RECORD
