Metadata-Version: 1.1
Name: python-pdf
Version: 0.38
Summary: PDF generation in python using wkhtmltopdf suitable for heroku
Home-page: https://github.com/tutorcruncher/pydf
Author: Samuel Colvin
Author-email: s@muelcolvin.com
License: MIT
Platform: any
Classifier: Development Status :: 5 - Production/Stable
Classifier: Environment :: Web Environment
Classifier: Intended Audience :: Developers
Classifier: License :: OSI Approved :: MIT License
Classifier: Programming Language :: Python
Classifier: Programming Language :: Python :: 3
Classifier: Programming Language :: Python :: 3.6
Classifier: Topic :: Internet :: WWW/HTTP
